Analysis/Missing_Value.py
Analysis/__init__.py
Missing_Value-0.2.5.dist-info/METADATA
Missing_Value-0.2.5.dist-info/WHEEL
Missing_Value-0.2.5.dist-info/top_level.txt
Missing_Value-0.2.5.dist-info/RECORD
